tradeview/__init__.py
tradeview-1.0.0.dev0.dist-info/METADATA
tradeview-1.0.0.dev0.dist-info/WHEEL
tradeview-1.0.0.dev0.dist-info/top_level.txt
tradeview-1.0.0.dev0.dist-info/RECORD
